[
    {
        "name": "Дизайн", 
        "childs": [
            {
                "subName":"Логотип и брендинг",
                "subChilds": [
                    {"subChildName":"Логотипы"}
                ] 
            },
            {
                "subName":"Арт и иллюстрации",
                "subChilds": [
                    {"subChildName":"John"},
                    {"subChildName":"sdfef"}
                ] 
            }
        ]
    },
    {
        "name": "gfh", 
        "childs": [
            {"name":"John", "age":30, "car":null},
            {"name":"sdfef", "age":36, "car":null}
        ]
    }
]